mrg_gitlab_template/.gitattributes
mrg_gitlab_template/.gitchangelog.rc
mrg_gitlab_template/.gitignore
mrg_gitlab_template/.gitlab-ci.yml
mrg_gitlab_template/AUTHORS.rst
mrg_gitlab_template/CHANGELOG.rst
mrg_gitlab_template/LICENSE
mrg_gitlab_template/MANIFEST.in
mrg_gitlab_template/README.css
mrg_gitlab_template/README.rst
mrg_gitlab_template/__init__.py
mrg_gitlab_template/icon.png
mrg_gitlab_template/pages.rst
mrg_gitlab_template/pylint.cfg
mrg_gitlab_template/requirements-dev.txt
mrg_gitlab_template/requirements.txt
mrg_gitlab_template/setup.cfg
mrg_gitlab_template/setup.py
mrg_gitlab_template/tox.ini
mrg_gitlab_template/versioneer.py
mrg_gitlab_template/docs/Makefile
mrg_gitlab_template/docs/README.rst
mrg_gitlab_template/docs/make.bat
mrg_gitlab_template/docs/requirements-docs.txt
mrg_gitlab_template/docs/source/acronyms.rst
mrg_gitlab_template/docs/source/api.rst
mrg_gitlab_template/docs/source/changelog.rst
mrg_gitlab_template/docs/source/conf.py
mrg_gitlab_template/docs/source/examples.rst
mrg_gitlab_template/docs/source/faq.rst
mrg_gitlab_template/docs/source/index.rst
mrg_gitlab_template/docs/source/install.rst
mrg_gitlab_template/docs/source/overview.rst
mrg_gitlab_template/docs/source/_static/example.puml
mrg_gitlab_template/examples/basic_example.py
mrg_gitlab_template/examples/support/__init__.py
mrg_gitlab_template/package/__init__.py
mrg_gitlab_template/package/_version.py
mrg_gitlab_template/package/run.py
mrg_gitlab_template/tests/__init__.py
mrg_gitlab_template/tests/test_package.py
mrg_gitlab_template-0.6.3.dist-info/DESCRIPTION.rst
mrg_gitlab_template-0.6.3.dist-info/METADATA
mrg_gitlab_template-0.6.3.dist-info/RECORD
mrg_gitlab_template-0.6.3.dist-info/WHEEL
mrg_gitlab_template-0.6.3.dist-info/entry_points.txt
mrg_gitlab_template-0.6.3.dist-info/metadata.json
mrg_gitlab_template-0.6.3.dist-info/top_level.txt
